doubutsushogi/__init__.py
doubutsushogi/ai.py
doubutsushogi/evaluate.py
doubutsushogi/game.py
doubutsushogi/images.py
doubutsushogi/pieces/emoji1/hiyoko.png
doubutsushogi/pieces/emoji1/kirin.png
doubutsushogi/pieces/emoji1/lion.png
doubutsushogi/pieces/emoji1/tori.png
doubutsushogi/pieces/emoji1/zou.png
doubutsushogi/pieces/emoji2/hiyoko.png
doubutsushogi/pieces/emoji2/kirin.png
doubutsushogi/pieces/emoji2/lion.png
doubutsushogi/pieces/emoji2/tori.png
doubutsushogi/pieces/emoji2/zou.png
doubutsushogi/pieces/emoji3/hiyoko.png
doubutsushogi/pieces/emoji3/kirin.png
doubutsushogi/pieces/emoji3/lion.png
doubutsushogi/pieces/emoji3/tori.png
doubutsushogi/pieces/emoji3/zou.png
doubutsushogi/pieces/hiragana/hiyoko.png
doubutsushogi/pieces/hiragana/kirin.png
doubutsushogi/pieces/hiragana/lion.png
doubutsushogi/pieces/hiragana/tori.png
doubutsushogi/pieces/hiragana/zou.png
doubutsushogi-0.0.5.dist-info/METADATA
doubutsushogi-0.0.5.dist-info/WHEEL
doubutsushogi-0.0.5.dist-info/top_level.txt
doubutsushogi-0.0.5.dist-info/RECORD
