Metadata-Version: 2.1
Name: doubutsushogi
Version: 0.0.5
Summary: Doubutsu shogi AI
Home-page: https://github.com/kota7/doubutsushogi-py
Author: Kota Mori
Author-email: kmori05@gmail.com
License: UNKNOWN
Platform: UNKNOWN
Classifier: Development Status :: 3 - Alpha
Classifier: Intended Audience :: Science/Research
Classifier: Topic :: Scientific/Engineering :: Artificial Intelligence
Classifier: Programming Language :: Python :: 3.6
Classifier: Programming Language :: Python :: 3.7
Requires-Dist: htmlwebshot
Requires-Dist: pillow
